<?xml version='1.0' encoding='UTF-8'?>
<base_palabras2>
    <palabra>
        <id>1</id>
        <contenido>a</contenido>
        <url>https://media.giphy.com/media/U8NJLUisdJ5JbX81bS/giphy.gif</url>
    </palabra>
    <palabra>
        <id>2</id>
        <contenido>b</contenido>
        <url>https://media.giphy.com/media/26gscSULUcfKU7dHq/giphy.gif</url>
    </palabra>
    <palabra>
        <id>3</id>
        <contenido>c</contenido>
        <url>https://media.giphy.com/media/26gsvly3OshqbUcog/giphy.gif</url>
    </palabra>
    <palabra>
        <id>4</id>
        <contenido>d</contenido>
        <url>https://media.giphy.com/media/d78vbBA54uHFS/giphy.gif</url>
    </palabra>
    <palabra>
        <id>5</id>
        <contenido>e</contenido>
        <url>https://media.giphy.com/media/l4FGEq97FqIjo3Ci4/giphy.gif</url>
    </palabra>
    <palabra>
        <id>6</id>
        <contenido>f</contenido>
        <url>https://media.giphy.com/media/hStvd5LiWCFzYNyxR4/giphy.gif</url>
    </palabra>
    <palabra>
        <id>7</id>
        <contenido>g</contenido>
        <url>https://media.giphy.com/media/cL4Q9j7rJCTDKXzSLy/giphy.gif</url>
    </palabra>
    <palabra>
        <id>8</id>
        <contenido>h</contenido>
        <url>Cristabel</url>
    </palabra>
    <palabra>
        <id>9</id>
        <contenido>i</contenido>
        <url>Althea</url>
    </palabra>
    <palabra>
        <id>10</id>
        <contenido>j</contenido>
        <url>Margery</url>
    </palabra>
    <palabra>
        <id>11</id>
        <contenido>k</contenido>
        <url>Anderea</url>
    </palabra>
    <palabra>
        <id>12</id>
        <contenido>l</contenido>
        <url>Magdalen</url>
    </palabra>
    <palabra>
        <id>13</id>
        <contenido>m</contenido>
        <url>Rozanne</url>
    </palabra>
    <palabra>
        <id>14</id>
        <contenido>n</contenido>
        <url>Ora</url>
    </palabra>
    <palabra>
        <id>15</id>
        <contenido>o</contenido>
        <url>Nessie</url>
    </palabra>
    <palabra>
        <id>16</id>
        <contenido>p</contenido>
        <url>Annemarie</url>
    </palabra>
    <palabra>
        <id>17</id>
        <contenido>q</contenido>
        <url>Norean</url>
    </palabra>
    <palabra>
        <id>18</id>
        <contenido>r</contenido>
        <url>Sarina</url>
    </palabra>
    <palabra>
        <id>19</id>
        <contenido>s</contenido>
        <url>Chelsae</url>
    </palabra>
    <palabra>
        <id>20</id>
        <contenido>t</contenido>
        <url>Stephannie</url>
    </palabra>
    <palabra>
        <id>21</id>
        <contenido>u</contenido>
        <url>Kata</url>
    </palabra>
    <palabra>
        <id>22</id>
        <contenido>v</contenido>
        <url>Jenilee</url>
    </palabra>
    <palabra>
        <id>23</id>
        <contenido>x</contenido>
        <url>Binnie</url>
    </palabra>
    <palabra>
        <id>24</id>
        <contenido>y</contenido>
        <url>Kaja</url>
    </palabra>
    <palabra>
        <id>25</id>
        <contenido>z</contenido>
        <url>Timothea</url>
    </palabra>
    <palabra>
        <id>26</id>
        <contenido>Chrisy</contenido>
        <url>Maressa</url>
    </palabra>
    <palabra>
        <id>27</id>
        <contenido>Hilliard</contenido>
        <url>Heidi</url>
    </palabra>
    <palabra>
        <id>28</id>
        <contenido>Giovanni</contenido>
        <url>Judi</url>
    </palabra>
    <palabra>
        <id>29</id>
        <contenido>Adham</contenido>
        <url>Gianna</url>
    </palabra>
    <palabra>
        <id>30</id>
        <contenido>Adolph</contenido>
        <url>Gerhardine</url>
    </palabra>
</base_palabras2>